Workbook

Sheet ポートフォリオ実績
A1: 【入力用】ここにサンプルデータと同様の形式でデータを貼り付け
A2: 年月 | B2: 資産クラス | C2: 簿価 | D2: 時価 | E2: インカム収益額 | F2: キャピタル収益額
A3: 44651 | B3: 国内債券（固定金利・国債中心） | C3: 49000 | D3: 50185.06 | E3: 0 | F3: 0
A4: 44681 | B4: 国内債券（固定金利・国債中心） | C4: 49408.68 | D4: 50595.51 | E4: 37.95 | F4: 0
A5: 44712 | B5: 国内債券（固定金利・国債中心） | C5: 49634.19 | D5: 51310.25 | E5: 38.12 | F5: 0
A6: 44742 | B6: 国内債券（固定金利・国債中心） | C6: 49478.82 | D6: 51495.96 | E6: 38.37 | F6: 0
A7: 44773 | B7: 国内債券（固定金利・国債中心） | C7: 49270.41 | D7: 51490.95 | E7: 38.47 | F7: 0
A8: 44804 | B8: 国内債券（固定金利・国債中心） | C8: 48468.05 | D8: 50460.39 | E8: 38.02 | F8: 0
A9: 44834 | B9: 国内債券（固定金利・国債中心） | C9: 48336.16 | D9: 50207.06 | E9: 37.75 | F9: 0
A10: 44865 | B10: 国内債券（固定金利・国債中心） | C10: 49155.7 | D10: 50850.4 | E10: 38.27 | F10: 0
A11: 44895 | B11: 国内債券（固定金利・国債中心） | C11: 45487.76 | D11: 47169.79 | E11: 39.18 | F11: -11.88
A12: 44926 | B12: 国内債券（固定金利・国債中心） | C12: 45023.46 | D12: 46850.71 | E12: 35.03 | F12: 0
A13: 44957 | B13: 国内債券（固定金利・国債中心） | C13: 44820.32 | D13: 46787.63 | E13: 34.99 | F13: 0
A14: 44985 | B14: 国内債券（固定金利・国債中心） | C14: 44616.77 | D14: 46877.72 | E14: 34.94 | F14: 0
... A261: 45747 | B261: （参考）政策保有株式 | C261: 8100.94 | D261: 9693.72 | E261: 16.49 | F261: 0

Sheet ベンチマークリターン
A1: 【入力用】
A2: 年月 | B2: ベンチマーク名 | C2: 月次リターン (%)
A3: 44681 | B3: NOMURA-BPI総合 | C3: -0.5398
A4: 44712 | B4: NOMURA-BPI総合 | C4: 0.3841
A5: 44742 | B5: NOMURA-BPI総合 | C5: -0.1371
A6: 44773 | B6: NOMURA-BPI総合 | C6: 0.23
A7: 44804 | B7: NOMURA-BPI総合 | C7: -0.6807
A8: 44834 | B8: NOMURA-BPI総合 | C8: 0.5752
A9: 44865 | B9: NOMURA-BPI総合 | C9: -0.0651
A10: 44895 | B10: NOMURA-BPI総合 | C10: -0.2601
A11: 44926 | B11: NOMURA-BPI総合 | C11: 0.6473
A12: 44957 | B12: NOMURA-BPI総合 | C12: -0.365
A13: 44985 | B13: NOMURA-BPI総合 | C13: -0.7715
A14: 45016 | B14: NOMURA-BPI総合 | C14: -0.8571
... A218: 45747 | B218: バランス型指数 | C218: 2.2384

Sheet 基準資産配分（設定）
A1: 【入力用】注意: 評価対象資産の「基準配分比率 (%)」の合計が100%になるよう調整
A2: 資産クラス | B2: 基準配分比率 (%) | C2: 対応ベンチマーク名
A3: 国内債券（固定金利・国債中心） | B3: 39.06 | C3: NOMURA-BPI総合
A4: 国内債券（変動/ASW） | B4: 15.62 | C4: TONA複利
A5: 外国債券（為替ヘッジ有・固定） | B5: 23.44 | C5: FTSE世界国債（除日、円H）
A6: 国内株式（純投資） | B6: 11.72 | C6: TOPIX（配当込み）
A7: 不動産（J-REIT含む） | B7: 3.91 | C7: 東証REIT指数（配当込み）
A8: マルチアセット・その他投信 | B8: 6.25 | C8: バランス型指数
A9: （参考）政策保有株式 | C9: TOPIX（配当込み）

Sheet 計算シート
A1: 年月 | B1: 資産クラス | C1: 簿価 | D1: 時価 | E1: インカム | F1: キャピタル | G1: 前月年月 | H1: 前月時価 | I1: 前月簿価 | J1: 当月評価損益 | K1: 前月評価損益 | L1: 評価損益変動 | M1: トータル収益額 | N1: 逆算CF | O1: 平均投資元本 | P1: 月次リターン(Rp) | Q1: BM名 | R1: 基準配分(Wb) | S1: BMリターン(Rb) | T1: 全体の前月時価(月) | U1: 実際配分(Wp) | V1: Rp_weighted | W1: Rb_weighted_policy
A2: =IF(ポートフォリオ実績!A3="","", ポートフォリオ実績!A3) -> 44651 | B2: =IF(ポートフォリオ実績!B3="","", ポートフォリオ実績!B3) -> 国内債券（固定金利・国債中心） | C2: =IF(ポートフォリオ実績!C3="","", ポートフォリオ実績!C3) -> 49000 | D2: =IF(ポートフォリオ実績!D3="","", ポートフォリオ実績!D3) -> 50185.06 | E2: =IF(ポートフォリオ実績!E3="","", ポートフォリオ実績!E3) -> 0 | F2: =IF(ポートフォリオ実績!F3="","", ポートフォリオ実績!F3) -> 0 | G2: =IF(A2<>"", EOMONTH(A2, -1), "") -> 44620 | H2: =IF(B2<>"", SUMIFS(ポートフォリオ実績!$D$2:$D$2001, ポートフォリオ実績!$B$2:$B$2001, B2, ポートフォリオ実績!$A$2:$A$2001, G2), 0) -> 0 | I2: =IF(B2<>"", SUMIFS(ポートフォリオ実績!$C$2:$C$2001, ポートフォリオ実績!$B$2:$B$2001, B2, ポートフォリオ実績!$A$2:$A$2001, G2), 0) -> 0 | J2: =IF(A2<>"", D2-C2, 0) -> 1185.06 | K2: =IF(A2<>"", H2-I2, 0) -> 0 | L2: =IF(H2=0, 0, J2-K2) -> 0 | M2: =IF(A2<>"", E2+F2+L2, 0) -> 0 | N2: =IF(H2=0, 0, (D2-H2)-M2) -> 0 | O2: =IF(A2<>"", H2+N2*0.5, 0) -> 0 | P2: =IF(A2="","", IF(O2>0.000001, M2/O2, IF(ABS(M2)<0.000001, 0, 0))) -> 0 | Q2: =IF(B2="","", IFERROR(VLOOKUP(B2, '基準資産配分（設定）'!$A$2:$C$2001, 3, FALSE), "")) -> NOMURA-BPI総合 | R2: =IF(B2="","", IFERROR(VLOOKUP(B2, '基準資産配分（設定）'!$A$2:$C$2001, 2, FALSE)/100, 0)) -> 0.3906 | S2: =IF(B2="","", IFERROR(SUMIFS(ベンチマークリターン!$C$2:$C$2001, ベンチマークリターン!$A$2:$A$2001, A2, ベンチマークリターン!$B$2:$B$2001, Q2) / 100, 0)) -> 0 | T2: =IF(A2="","", SUMIFS($H$2:$H$2000, $A$2:$A$2000, A2)) -> 0 | U2: =IF(A2="","", IFERROR(H2/T2, 0)) -> 0 | V2: =IF(A2="","", U2*P2) -> 0 | W2: =IF(A2="","", R2*S2) -> 0
A3: =IF(ポートフォリオ実績!A4="","", ポートフォリオ実績!A4) -> 44681 | B3: =IF(ポートフォリオ実績!B4="","", ポートフォリオ実績!B4) -> 国内債券（固定金利・国債中心） | C3: =IF(ポートフォリオ実績!C4="","", ポートフォリオ実績!C4) -> 49408.68 | D3: =IF(ポートフォリオ実績!D4="","", ポートフォリオ実績!D4) -> 50595.51 | E3: =IF(ポートフォリオ実績!E4="","", ポートフォリオ実績!E4) -> 37.95 | F3: =IF(ポートフォリオ実績!F4="","", ポートフォリオ実績!F4) -> 0 | G3: =IF(A3<>"", EOMONTH(A3, -1), "") -> 44651 | H3: =IF(B3<>"", SUMIFS(ポートフォリオ実績!$D$2:$D$2001, ポートフォリオ実績!$B$2:$B$2001, B3, ポートフォリオ実績!$A$2:$A$2001, G3), 0) -> 50185.06 | I3: =IF(B3<>"", SUMIFS(ポートフォリオ実績!$C$2:$C$2001, ポートフォリオ実績!$B$2:$B$2001, B3, ポートフォリオ実績!$A$2:$A$2001, G3), 0) -> 49000 | J3: =IF(A3<>"", D3-C3, 0) -> 1186.83 | K3: =IF(A3<>"", H3-I3, 0) -> 1185.06 | L3: =IF(H3=0, 0, J3-K3) -> 1.77 | M3: =IF(A3<>"", E3+F3+L3, 0) -> 39.72 | N3: =IF(H3=0, 0, (D3-H3)-M3) -> 370.73 | O3: =IF(A3<>"", H3+N3*0.5, 0) -> 50370.425 | P3: =IF(A3="","", IF(O3>0.000001, M3/O3, IF(ABS(M3)<0.000001, 0, 0))) -> 0.00078855797 | Q3: =IF(B3="","", IFERROR(VLOOKUP(B3, '基準資産配分（設定）'!$A$2:$C$2001, 3, FALSE), "")) -> NOMURA-BPI総合 | R3: =IF(B3="","", IFERROR(VLOOKUP(B3, '基準資産配分（設定）'!$A$2:$C$2001, 2, FALSE)/100, 0)) -> 0.3906 | S3: =IF(B3="","", IFERROR(SUMIFS(ベンチマークリターン!$C$2:$C$2001, ベンチマークリターン!$A$2:$A$2001, A3, ベンチマークリターン!$B$2:$B$2001, Q3) / 100, 0)) -> -0.005398 | T3: =IF(A3="","", SUMIFS($H$2:$H$2000, $A$2:$A$2000, A3)) -> 139117.94 | U3: =IF(A3="","", IFERROR(H3/T3, 0)) -> 0.36073752 | V3: =IF(A3="","", U3*P3) -> 0.00028446244 | W3: =IF(A3="","", R3*S3) -> -0.0021084588
A4: =IF(ポートフォリオ実績!A5="","", ポートフォリオ実績!A5) -> 44712 | B4: =IF(ポートフォリオ実績!B5="","", ポートフォリオ実績!B5) -> 国内債券（固定金利・国債中心） | C4: =IF(ポートフォリオ実績!C5="","", ポートフォリオ実績!C5) -> 49634.19 | D4: =IF(ポートフォリオ実績!D5="","", ポートフォリオ実績!D5) -> 51310.25 | E4: =IF(ポートフォリオ実績!E5="","", ポートフォリオ実績!E5) -> 38.12 | F4: =IF(ポートフォリオ実績!F5="","", ポートフォリオ実績!F5) -> 0 | G4: =IF(A4<>"", EOMONTH(A4, -1), "") -> 44681 | H4: =IF(B4<>"", SUMIFS(ポートフォリオ実績!$D$2:$D$2001, ポートフォリオ実績!$B$2:$B$2001, B4, ポートフォリオ実績!$A$2:$A$2001, G4), 0) -> 50595.51 | I4: =IF(B4<>"", SUMIFS(ポートフォリオ実績!$C$2:$C$2001, ポートフォリオ実績!$B$2:$B$2001, B4, ポートフォリオ実績!$A$2:$A$2001, G4), 0) -> 49408.68 | J4: =IF(A4<>"", D4-C4, 0) -> 1676.06 | K4: =IF(A4<>"", H4-I4, 0) -> 1186.83 | L4: =IF(H4=0, 0, J4-K4) -> 489.23 | M4: =IF(A4<>"", E4+F4+L4, 0) -> 527.35 | N4: =IF(H4=0, 0, (D4-H4)-M4) -> 187.39 | O4: =IF(A4<>"", H4+N4*0.5, 0) -> 50689.205 | P4: =IF(A4="","", IF(O4>0.000001, M4/O4, IF(ABS(M4)<0.000001, 0, 0))) -> 0.010403596 | Q4: =IF(B4="","", IFERROR(VLOOKUP(B4, '基準資産配分（設定）'!$A$2:$C$2001, 3, FALSE), "")) -> NOMURA-BPI総合 | R4: =IF(B4="","", IFERROR(VLOOKUP(B4, '基準資産配分（設定）'!$A$2:$C$2001, 2, FALSE)/100, 0)) -> 0.3906 | S4: =IF(B4="","", IFERROR(SUMIFS(ベンチマークリターン!$C$2:$C$2001, ベンチマークリターン!$A$2:$A$2001, A4, ベンチマークリターン!$B$2:$B$2001, Q4) / 100, 0)) -> 0.003841 | T4: =IF(A4="","", SUMIFS($H$2:$H$2000, $A$2:$A$2000, A4)) -> 139899.38 | U4: =IF(A4="","", IFERROR(H4/T4, 0)) -> 0.36165643 | V4: =IF(A4="","", U4*P4) -> 0.0037625273 | W4: =IF(A4="","", R4*S4) -> 0.0015002946
A5: =IF(ポートフォリオ実績!A6="","", ポートフォリオ実績!A6) -> 44742 | B5: =IF(ポートフォリオ実績!B6="","", ポートフォリオ実績!B6) -> 国内債券（固定金利・国債中心） | C5: =IF(ポートフォリオ実績!C6="","", ポートフォリオ実績!C6) -> 49478.82 | D5: =IF(ポートフォリオ実績!D6="","", ポートフォリオ実績!D6) -> 51495.96 | E5: =IF(ポートフォリオ実績!E6="","", ポートフォリオ実績!E6) -> 38.37 | F5: =IF(ポートフォリオ実績!F6="","", ポートフォリオ実績!F6) -> 0 | G5: =IF(A5<>"", EOMONTH(A5, -1), "") -> 44712 | H5: =IF(B5<>"", SUMIFS(ポートフォリオ実績!$D$2:$D$2001, ポートフォリオ実績!$B$2:$B$2001, B5, ポートフォリオ実績!$A$2:$A$2001, G5), 0) -> 51310.25 | I5: =IF(B5<>"", SUMIFS(ポートフォリオ実績!$C$2:$C$2001, ポートフォリオ実績!$B$2:$B$2001, B5, ポートフォリオ実績!$A$2:$A$2001, G5), 0) -> 49634.19 | J5: =IF(A5<>"", D5-C5, 0) -> 2017.14 | K5: =IF(A5<>"", H5-I5, 0) -> 1676.06 | L5: =IF(H5=0, 0, J5-K5) -> 341.08 | M5: =IF(A5<>"", E5+F5+L5, 0) -> 379.45 | N5: =IF(H5=0, 0, (D5-H5)-M5) -> -193.74 | O5: =IF(A5<>"", H5+N5*0.5, 0) -> 51213.38 | P5: =IF(A5="","", IF(O5>0.000001, M5/O5, IF(ABS(M5)<0.000001, 0, 0))) -> 0.0074091966 | Q5: =IF(B5="","", IFERROR(VLOOKUP(B5, '基準資産配分（設定）'!$A$2:$C$2001, 3, FALSE), "")) -> NOMURA-BPI総合 | R5: =IF(B5="","", IFERROR(VLOOKUP(B5, '基準資産配分（設定）'!$A$2:$C$2001, 2, FALSE)/100, 0)) -> 0.3906 | S5: =IF(B5="","", IFERROR(SUMIFS(ベンチマークリターン!$C$2:$C$2001, ベンチマークリターン!$A$2:$A$2001, A5, ベンチマークリターン!$B$2:$B$2001, Q5) / 100, 0)) -> -0.001371 | T5: =IF(A5="","", SUMIFS($H$2:$H$2000, $A$2:$A$2000, A5)) -> 143058.46 | U5: =IF(A5="","", IFERROR(H5/T5, 0)) -> 0.35866631 | V5: =IF(A5="","", U5*P5) -> 0.0026574292 | W5: =IF(A5="","", R5*S5) -> -0.0005355126
A6: =IF(ポートフォリオ実績!A7="","", ポートフォリオ実績!A7) -> 44773 | B6: =IF(ポートフォリオ実績!B7="","", ポートフォリオ実績!B7) -> 国内債券（固定金利・国債中心） | C6: =IF(ポートフォリオ実績!C7="","", ポートフォリオ実績!C7) -> 49270.41 | D6: =IF(ポートフォリオ実績!D7="","", ポートフォリオ実績!D7) -> 51490.95 | E6: =IF(ポートフォリオ実績!E7="","", ポートフォリオ実績!E7) -> 38.47 | F6: =IF(ポートフォリオ実績!F7="","", ポートフォリオ実績!F7) -> 0 | G6: =IF(A6<>"", EOMONTH(A6, -1), "") -> 44742 | H6: =IF(B6<>"", SUMIFS(ポートフォリオ実績!$D$2:$D$2001, ポートフォリオ実績!$B$2:$B$2001, B6, ポートフォリオ実績!$A$2:$A$2001, G6), 0) -> 51495.96 | I6: =IF(B6<>"", SUMIFS(ポートフォリオ実績!$C$2:$C$2001, ポートフォリオ実績!$B$2:$B$2001, B6, ポートフォリオ実績!$A$2:$A$2001, G6), 0) -> 49478.82 | J6: =IF(A6<>"", D6-C6, 0) -> 2220.54 | K6: =IF(A6<>"", H6-I6, 0) -> 2017.14 | L6: =IF(H6=0, 0, J6-K6) -> 203.4 | M6: =IF(A6<>"", E6+F6+L6, 0) -> 241.87 | N6: =IF(H6=0, 0, (D6-H6)-M6) -> -246.88 | O6: =IF(A6<>"", H6+N6*0.5, 0) -> 51372.52 | P6: =IF(A6="","", IF(O6>0.000001, M6/O6, IF(ABS(M6)<0.000001, 0, 0))) -> 0.0047081591 | Q6: =IF(B6="","", IFERROR(VLOOKUP(B6, '基準資産配分（設定）'!$A$2:$C$2001, 3, FALSE), "")) -> NOMURA-BPI総合 | R6: =IF(B6="","", IFERROR(VLOOKUP(B6, '基準資産配分（設定）'!$A$2:$C$2001, 2, FALSE)/100, 0)) -> 0.3906 | S6: =IF(B6="","", IFERROR(SUMIFS(ベンチマークリターン!$C$2:$C$2001, ベンチマークリターン!$A$2:$A$2001, A6, ベンチマークリターン!$B$2:$B$2001, Q6) / 100, 0)) -> 0.0023 | T6: =IF(A6="","", SUMIFS($H$2:$H$2000, $A$2:$A$2000, A6)) -> 143829.51 | U6: =IF(A6="","", IFERROR(H6/T6, 0)) -> 0.35803473 | V6: =IF(A6="","", U6*P6) -> 0.0016856845 | W6: =IF(A6="","", R6*S6) -> 0.00089838
A7: =IF(ポートフォリオ実績!A8="","", ポートフォリオ実績!A8) -> 44804 | B7: =IF(ポートフォリオ実績!B8="","", ポートフォリオ実績!B8) -> 国内債券（固定金利・国債中心） | C7: =IF(ポートフォリオ実績!C8="","", ポートフォリオ実績!C8) -> 48468.05 | D7: =IF(ポートフォリオ実績!D8="","", ポートフォリオ実績!D8) -> 50460.39 | E7: =IF(ポートフォリオ実績!E8="","", ポートフォリオ実績!E8) -> 38.02 | F7: =IF(ポートフォリオ実績!F8="","", ポートフォリオ実績!F8) -> 0 | G7: =IF(A7<>"", EOMONTH(A7, -1), "") -> 44773 | H7: =IF(B7<>"", SUMIFS(ポートフォリオ実績!$D$2:$D$2001, ポートフォリオ実績!$B$2:$B$2001, B7, ポートフォリオ実績!$A$2:$A$2001, G7), 0) -> 51490.95 | I7: =IF(B7<>"", SUMIFS(ポートフォリオ実績!$C$2:$C$2001, ポートフォリオ実績!$B$2:$B$2001, B7, ポートフォリオ実績!$A$2:$A$2001, G7), 0) -> 49270.41 | J7: =IF(A7<>"", D7-C7, 0) -> 1992.34 | K7: =IF(A7<>"", H7-I7, 0) -> 2220.54 | L7: =IF(H7=0, 0, J7-K7) -> -228.2 | M7: =IF(A7<>"", E7+F7+L7, 0) -> -190.18 | N7: =IF(H7=0, 0, (D7-H7)-M7) -> -840.38 | O7: =IF(A7<>"", H7+N7*0.5, 0) -> 51070.76 | P7: =IF(A7="","", IF(O7>0.000001, M7/O7, IF(ABS(M7)<0.000001, 0, 0))) -> -0.0037238529 | Q7: =IF(B7="","", IFERROR(VLOOKUP(B7, '基準資産配分（設定）'!$A$2:$C$2001, 3, FALSE), "")) -> NOMURA-BPI総合 | R7: =IF(B7="","", IFERROR(VLOOKUP(B7, '基準資産配分（設定）'!$A$2:$C$2001, 2, FALSE)/100, 0)) -> 0.3906 | S7: =IF(B7="","", IFERROR(SUMIFS(ベンチマークリターン!$C$2:$C$2001, ベンチマークリターン!$A$2:$A$2001, A7, ベンチマークリターン!$B$2:$B$2001, Q7) / 100, 0)) -> -0.006807 | T7: =IF(A7="","", SUMIFS($H$2:$H$2000, $A$2:$A$2000, A7)) -> 145658.63 | U7: =IF(A7="","", IFERROR(H7/T7, 0)) -> 0.35350429 | V7: =IF(A7="","", U7*P7) -> -0.001316398 | W7: =IF(A7="","", R7*S7) -> -0.0026588142
A8: =IF(ポートフォリオ実績!A9="","", ポートフォリオ実績!A9) -> 44834 | B8: =IF(ポートフォリオ実績!B9="","", ポートフォリオ実績!B9) -> 国内債券（固定金利・国債中心） | C8: =IF(ポートフォリオ実績!C9="","", ポートフォリオ実績!C9) -> 48336.16 | D8: =IF(ポートフォリオ実績!D9="","", ポートフォリオ実績!D9) -> 50207.06 | E8: =IF(ポートフォリオ実績!E9="","", ポートフォリオ実績!E9) -> 37.75 | F8: =IF(ポートフォリオ実績!F9="","", ポートフォリオ実績!F9) -> 0 | G8: =IF(A8<>"", EOMONTH(A8, -1), "") -> 44804 | H8: =IF(B8<>"", SUMIFS(ポートフォリオ実績!$D$2:$D$2001, ポートフォリオ実績!$B$2:$B$2001, B8, ポートフォリオ実績!$A$2:$A$2001, G8), 0) -> 50460.39 | I8: =IF(B8<>"", SUMIFS(ポートフォリオ実績!$C$2:$C$2001, ポートフォリオ実績!$B$2:$B$2001, B8, ポートフォリオ実績!$A$2:$A$2001, G8), 0) -> 48468.05 | J8: =IF(A8<>"", D8-C8, 0) -> 1870.9 | K8: =IF(A8<>"", H8-I8, 0) -> 1992.34 | L8: =IF(H8=0, 0, J8-K8) -> -121.44 | M8: =IF(A8<>"", E8+F8+L8, 0) -> -83.69 | N8: =IF(H8=0, 0, (D8-H8)-M8) -> -169.64 | O8: =IF(A8<>"", H8+N8*0.5, 0) -> 50375.57 | P8: =IF(A8="","", IF(O8>0.000001, M8/O8, IF(ABS(M8)<0.000001, 0, 0))) -> -0.0016613212 | Q8: =IF(B8="","", IFERROR(VLOOKUP(B8, '基準資産配分（設定）'!$A$2:$C$2001, 3, FALSE), "")) -> NOMURA-BPI総合 | R8: =IF(B8="","", IFERROR(VLOOKUP(B8, '基準資産配分（設定）'!$A$2:$C$2001, 2, FALSE)/100, 0)) -> 0.3906 | S8: =IF(B8="","", IFERROR(SUMIFS(ベンチマークリターン!$C$2:$C$2001, ベンチマークリターン!$A$2:$A$2001, A8, ベンチマークリターン!$B$2:$B$2001, Q8) / 100, 0)) -> 0.005752 | T8: =IF(A8="","", SUMIFS($H$2:$H$2000, $A$2:$A$2000, A8)) -> 144325.42 | U8: =IF(A8="","", IFERROR(H8/T8, 0)) -> 0.34962926 | V8: =IF(A8="","", U8*P8) -> -0.00058084649 | W8: =IF(A8="","", R8*S8) -> 0.0022467312
A9: =IF(ポートフォリオ実績!A10="","", ポートフォリオ実績!A10) -> 44865 | B9: =IF(ポートフォリオ実績!B10="","", ポートフォリオ実績!B10) -> 国内債券（固定金利・国債中心） | C9: =IF(ポートフォリオ実績!C10="","", ポートフォリオ実績!C10) -> 49155.7 | D9: =IF(ポートフォリオ実績!D10="","", ポートフォリオ実績!D10) -> 50850.4 | E9: =IF(ポートフォリオ実績!E10="","", ポートフォリオ実績!E10) -> 38.27 | F9: =IF(ポートフォリオ実績!F10="","", ポートフォリオ実績!F10) -> 0 | G9: =IF(A9<>"", EOMONTH(A9, -1), "") -> 44834 | H9: =IF(B9<>"", SUMIFS(ポートフォリオ実績!$D$2:$D$2001, ポートフォリオ実績!$B$2:$B$2001, B9, ポートフォリオ実績!$A$2:$A$2001, G9), 0) -> 50207.06 | I9: =IF(B9<>"", SUMIFS(ポートフォリオ実績!$C$2:$C$2001, ポートフォリオ実績!$B$2:$B$2001, B9, ポートフォリオ実績!$A$2:$A$2001, G9), 0) -> 48336.16 | J9: =IF(A9<>"", D9-C9, 0) -> 1694.7 | K9: =IF(A9<>"", H9-I9, 0) -> 1870.9 | L9: =IF(H9=0, 0, J9-K9) -> -176.2 | M9: =IF(A9<>"", E9+F9+L9, 0) -> -137.93 | N9: =IF(H9=0, 0, (D9-H9)-M9) -> 781.27 | O9: =IF(A9<>"", H9+N9*0.5, 0) -> 50597.695 | P9: =IF(A9="","", IF(O9>0.000001, M9/O9, IF(ABS(M9)<0.000001, 0, 0))) -> -0.0027260135 | Q9: =IF(B9="","", IFERROR(VLOOKUP(B9, '基準資産配分（設定）'!$A$2:$C$2001, 3, FALSE), "")) -> NOMURA-BPI総合 | R9: =IF(B9="","", IFERROR(VLOOKUP(B9, '基準資産配分（設定）'!$A$2:$C$2001, 2, FALSE)/100, 0)) -> 0.3906 | S9: =IF(B9="","", IFERROR(SUMIFS(ベンチマークリターン!$C$2:$C$2001, ベンチマークリターン!$A$2:$A$2001, A9, ベンチマークリターン!$B$2:$B$2001, Q9) / 100, 0)) -> -0.000651 | T9: =IF(A9="","", SUMIFS($H$2:$H$2000, $A$2:$A$2000, A9)) -> 145674.57 | U9: =IF(A9="","", IFERROR(H9/T9, 0)) -> 0.34465219 | V9: =IF(A9="","", U9*P9) -> -0.00093952653 | W9: =IF(A9="","", R9*S9) -> -0.0002542806
A10: =IF(ポートフォリオ実績!A11="","", ポートフォリオ実績!A11) -> 44895 | B10: =IF(ポートフォリオ実績!B11="","", ポートフォリオ実績!B11) -> 国内債券（固定金利・国債中心） | C10: =IF(ポートフォリオ実績!C11="","", ポートフォリオ実績!C11) -> 45487.76 | D10: =IF(ポートフォリオ実績!D11="","", ポートフォリオ実績!D11) -> 47169.79 | E10: =IF(ポートフォリオ実績!E11="","", ポートフォリオ実績!E11) -> 39.18 | F10: =IF(ポートフォリオ実績!F11="","", ポートフォリオ実績!F11) -> -11.88 | G10: =IF(A10<>"", EOMONTH(A10, -1), "") -> 44865 | H10: =IF(B10<>"", SUMIFS(ポートフォリオ実績!$D$2:$D$2001, ポートフォリオ実績!$B$2:$B$2001, B10, ポートフォリオ実績!$A$2:$A$2001, G10), 0) -> 50850.4 | I10: =IF(B10<>"", SUMIFS(ポートフォリオ実績!$C$2:$C$2001, ポートフォリオ実績!$B$2:$B$2001, B10, ポートフォリオ実績!$A$2:$A$2001, G10), 0) -> 49155.7 | J10: =IF(A10<>"", D10-C10, 0) -> 1682.03 | K10: =IF(A10<>"", H10-I10, 0) -> 1694.7 | L10: =IF(H10=0, 0, J10-K10) -> -12.67 | M10: =IF(A10<>"", E10+F10+L10, 0) -> 14.63 | N10: =IF(H10=0, 0, (D10-H10)-M10) -> -3695.24 | O10: =IF(A10<>"", H10+N10*0.5, 0) -> 49002.78 | P10: =IF(A10="","", IF(O10>0.000001, M10/O10, IF(ABS(M10)<0.000001, 0, 0))) -> 0.00029855449 | Q10: =IF(B10="","", IFERROR(VLOOKUP(B10, '基準資産配分（設定）'!$A$2:$C$2001, 3, FALSE), "")) -> NOMURA-BPI総合 | R10: =IF(B10="","", IFERROR(VLOOKUP(B10, '基準資産配分（設定）'!$A$2:$C$2001, 2, FALSE)/100, 0)) -> 0.3906 | S10: =IF(B10="","", IFERROR(SUMIFS(ベンチマークリターン!$C$2:$C$2001, ベンチマークリターン!$A$2:$A$2001, A10, ベンチマークリターン!$B$2:$B$2001, Q10) / 100, 0)) -> -0.002601 | T10: =IF(A10="","", SUMIFS($H$2:$H$2000, $A$2:$A$2000, A10)) -> 149722.51 | U10: =IF(A10="","", IFERROR(H10/T10, 0)) -> 0.33963096 | V10: =IF(A10="","", U10*P10) -> 0.00010139835 | W10: =IF(A10="","", R10*S10) -> -0.0010159506
A11: =IF(ポートフォリオ実績!A12="","", ポートフォリオ実績!A12) -> 44926 | B11: =IF(ポートフォリオ実績!B12="","", ポートフォリオ実績!B12) -> 国内債券（固定金利・国債中心） | C11: =IF(ポートフォリオ実績!C12="","", ポートフォリオ実績!C12) -> 45023.46 | D11: =IF(ポートフォリオ実績!D12="","", ポートフォリオ実績!D12) -> 46850.71 | E11: =IF(ポートフォリオ実績!E12="","", ポートフォリオ実績!E12) -> 35.03 | F11: =IF(ポートフォリオ実績!F12="","", ポートフォリオ実績!F12) -> 0 | G11: =IF(A11<>"", EOMONTH(A11, -1), "") -> 44895 | H11: =IF(B11<>"", SUMIFS(ポートフォリオ実績!$D$2:$D$2001, ポートフォリオ実績!$B$2:$B$2001, B11, ポートフォリオ実績!$A$2:$A$2001, G11), 0) -> 47169.79 | I11: =IF(B11<>"", SUMIFS(ポートフォリオ実績!$C$2:$C$2001, ポートフォリオ実績!$B$2:$B$2001, B11, ポートフォリオ実績!$A$2:$A$2001, G11), 0) -> 45487.76 | J11: =IF(A11<>"", D11-C11, 0) -> 1827.25 | K11: =IF(A11<>"", H11-I11, 0) -> 1682.03 | L11: =IF(H11=0, 0, J11-K11) -> 145.22 | M11: =IF(A11<>"", E11+F11+L11, 0) -> 180.25 | N11: =IF(H11=0, 0, (D11-H11)-M11) -> -499.33 | O11: =IF(A11<>"", H11+N11*0.5, 0) -> 46920.125 | P11: =IF(A11="","", IF(O11>0.000001, M11/O11, IF(ABS(M11)<0.000001, 0, 0))) -> 0.0038416351 | Q11: =IF(B11="","", IFERROR(VLOOKUP(B11, '基準資産配分（設定）'!$A$2:$C$2001, 3, FALSE), "")) -> NOMURA-BPI総合 | R11: =IF(B11="","", IFERROR(VLOOKUP(B11, '基準資産配分（設定）'!$A$2:$C$2001, 2, FALSE)/100, 0)) -> 0.3906 | S11: =IF(B11="","", IFERROR(SUMIFS(ベンチマークリターン!$C$2:$C$2001, ベンチマークリターン!$A$2:$A$2001, A11, ベンチマークリターン!$B$2:$B$2001, Q11) / 100, 0)) -> 0.006473 | T11: =IF(A11="","", SUMIFS($H$2:$H$2000, $A$2:$A$2000, A11)) -> 146745.92 | U11: =IF(A11="","", IFERROR(H11/T11, 0)) -> 0.32143851 | V11: =IF(A11="","", U11*P11) -> 0.0012348495 | W11: =IF(A11="","", R11*S11) -> 0.0025283538
A12: =IF(ポートフォリオ実績!A13="","", ポートフォリオ実績!A13) -> 44957 | B12: =IF(ポートフォリオ実績!B13="","", ポートフォリオ実績!B13) -> 国内債券（固定金利・国債中心） | C12: =IF(ポートフォリオ実績!C13="","", ポートフォリオ実績!C13) -> 44820.32 | D12: =IF(ポートフォリオ実績!D13="","", ポートフォリオ実績!D13) -> 46787.63 | E12: =IF(ポートフォリオ実績!E13="","", ポートフォリオ実績!E13) -> 34.99 | F12: =IF(ポートフォリオ実績!F13="","", ポートフォリオ実績!F13) -> 0 | G12: =IF(A12<>"", EOMONTH(A12, -1), "") -> 44926 | H12: =IF(B12<>"", SUMIFS(ポートフォリオ実績!$D$2:$D$2001, ポートフォリオ実績!$B$2:$B$2001, B12, ポートフォリオ実績!$A$2:$A$2001, G12), 0) -> 46850.71 | I12: =IF(B12<>"", SUMIFS(ポートフォリオ実績!$C$2:$C$2001, ポートフォリオ実績!$B$2:$B$2001, B12, ポートフォリオ実績!$A$2:$A$2001, G12), 0) -> 45023.46 | J12: =IF(A12<>"", D12-C12, 0) -> 1967.31 | K12: =IF(A12<>"", H12-I12, 0) -> 1827.25 | L12: =IF(H12=0, 0, J12-K12) -> 140.06 | M12: =IF(A12<>"", E12+F12+L12, 0) -> 175.05 | N12: =IF(H12=0, 0, (D12-H12)-M12) -> -238.13 | O12: =IF(A12<>"", H12+N12*0.5, 0) -> 46731.645 | P12: =IF(A12="","", IF(O12>0.000001, M12/O12, IF(ABS(M12)<0.000001, 0, 0))) -> 0.0037458557 | Q12: =IF(B12="","", IFERROR(VLOOKUP(B12, '基準資産配分（設定）'!$A$2:$C$2001, 3, FALSE), "")) -> NOMURA-BPI総合 | R12: =IF(B12="","", IFERROR(VLOOKUP(B12, '基準資産配分（設定）'!$A$2:$C$2001, 2, FALSE)/100, 0)) -> 0.3906 | S12: =IF(B12="","", IFERROR(SUMIFS(ベンチマークリターン!$C$2:$C$2001, ベンチマークリターン!$A$2:$A$2001, A12, ベンチマークリターン!$B$2:$B$2001, Q12) / 100, 0)) -> -0.00365 | T12: =IF(A12="","", SUMIFS($H$2:$H$2000, $A$2:$A$2000, A12)) -> 148588.96 | U12: =IF(A12="","", IFERROR(H12/T12, 0)) -> 0.31530411 | V12: =IF(A12="","", U12*P12) -> 0.0011810837 | W12: =IF(A12="","", R12*S12) -> -0.00142569
A13: =IF(ポートフォリオ実績!A14="","", ポートフォリオ実績!A14) -> 44985 | B13: =IF(ポートフォリオ実績!B14="","", ポートフォリオ実績!B14) -> 国内債券（固定金利・国債中心） | C13: =IF(ポートフォリオ実績!C14="","", ポートフォリオ実績!C14) -> 44616.77 | D13: =IF(ポートフォリオ実績!D14="","", ポートフォリオ実績!D14) -> 46877.72 | E13: =IF(ポートフォリオ実績!E14="","", ポートフォリオ実績!E14) -> 34.94 | F13: =IF(ポートフォリオ実績!F14="","", ポートフォリオ実績!F14) -> 0 | G13: =IF(A13<>"", EOMONTH(A13, -1), "") -> 44957 | H13: =IF(B13<>"", SUMIFS(ポートフォリオ実績!$D$2:$D$2001, ポートフォリオ実績!$B$2:$B$2001, B13, ポートフォリオ実績!$A$2:$A$2001, G13), 0) -> 46787.63 | I13: =IF(B13<>"", SUMIFS(ポートフォリオ実績!$C$2:$C$2001, ポートフォリオ実績!$B$2:$B$2001, B13, ポートフォリオ実績!$A$2:$A$2001, G13), 0) -> 44820.32 | J13: =IF(A13<>"", D13-C13, 0) -> 2260.95 | K13: =IF(A13<>"", H13-I13, 0) -> 1967.31 | L13: =IF(H13=0, 0, J13-K13) -> 293.64 | M13: =IF(A13<>"", E13+F13+L13, 0) -> 328.58 | N13: =IF(H13=0, 0, (D13-H13)-M13) -> -238.49 | O13: =IF(A13<>"", H13+N13*0.5, 0) -> 46668.385 | P13: =IF(A13="","", IF(O13>0.000001, M13/O13, IF(ABS(M13)<0.000001, 0, 0))) -> 0.0070407407 | Q13: =IF(B13="","", IFERROR(VLOOKUP(B13, '基準資産配分（設定）'!$A$2:$C$2001, 3, FALSE), "")) -> NOMURA-BPI総合 | R13: =IF(B13="","", IFERROR(VLOOKUP(B13, '基準資産配分（設定）'!$A$2:$C$2001, 2, FALSE)/100, 0)) -> 0.3906 | S13: =IF(B13="","", IFERROR(SUMIFS(ベンチマークリターン!$C$2:$C$2001, ベンチマークリターン!$A$2:$A$2001, A13, ベンチマークリターン!$B$2:$B$2001, Q13) / 100, 0)) -> -0.007715 | T13: =IF(A13="","", SUMIFS($H$2:$H$2000, $A$2:$A$2000, A13)) -> 149058.73 | U13: =IF(A13="","", IFERROR(H13/T13, 0)) -> 0.31388722 | V13: =IF(A13="","", U13*P13) -> 0.0022099985 | W13: =IF(A13="","", R13*S13) -> -0.003013479
... A2000: =IF(ポートフォリオ実績!A2001="","", ポートフォリオ実績!A2001) | B2000: =IF(ポートフォリオ実績!B2001="","", ポートフォリオ実績!B2001) | C2000: =IF(ポートフォリオ実績!C2001="","", ポートフォリオ実績!C2001) | D2000: =IF(ポートフォリオ実績!D2001="","", ポートフォリオ実績!D2001) | E2000: =IF(ポートフォリオ実績!E2001="","", ポートフォリオ実績!E2001) | F2000: =IF(ポートフォリオ実績!F2001="","", ポートフォリオ実績!F2001) | G2000: =IF(A2000<>"", EOMONTH(A2000, -1), "") | H2000: =IF(B2000<>"", SUMIFS(ポートフォリオ実績!$D$2:$D$2001, ポートフォリオ実績!$B$2:$B$2001, B2000, ポートフォリオ実績!$A$2:$A$2001, G2000), 0) -> 0 | I2000: =IF(B2000<>"", SUMIFS(ポートフォリオ実績!$C$2:$C$2001, ポートフォリオ実績!$B$2:$B$2001, B2000, ポートフォリオ実績!$A$2:$A$2001, G2000), 0) -> 0 | J2000: =IF(A2000<>"", D2000-C2000, 0) -> 0 | K2000: =IF(A2000<>"", H2000-I2000, 0) -> 0 | L2000: =IF(H2000=0, 0, J2000-K2000) -> 0 | M2000: =IF(A2000<>"", E2000+F2000+L2000, 0) -> 0 | N2000: =IF(H2000=0, 0, (D2000-H2000)-M2000) -> 0 | O2000: =IF(A2000<>"", H2000+N2000*0.5, 0) -> 0 | P2000: =IF(A2000="","", IF(O2000>0.000001, M2000/O2000, IF(ABS(M2000)<0.000001, 0, 0))) | Q2000: =IF(B2000="","", IFERROR(VLOOKUP(B2000, '基準資産配分（設定）'!$A$2:$C$2001, 3, FALSE), "")) | R2000: =IF(B2000="","", IFERROR(VLOOKUP(B2000, '基準資産配分（設定）'!$A$2:$C$2001, 2, FALSE)/100, 0)) | S2000: =IF(B2000="","", IFERROR(SUMIFS(ベンチマークリターン!$C$2:$C$2001, ベンチマークリターン!$A$2:$A$2001, A2000, ベンチマークリターン!$B$2:$B$2001, Q2000) / 100, 0)) | T2000: =IF(A2000="","", SUMIFS($H$2:$H$2000, $A$2:$A$2000, A2000)) | U2000: =IF(A2000="","", IFERROR(H2000/T2000, 0)) | V2000: =IF(A2000="","", U2000*P2000) | W2000: =IF(A2000="","", R2000*S2000)

Sheet ダッシュボード
A1: 月次・累積リターン（グラフ元） | G1: ブリンソン分解（算術平均ベース）
A2: 年月 | B2: 月次Rp(全体) | C2: 月次Rb(全体) | D2: 累積Rp(全体) | E2: 累積Rb(全体) | G2: 資産クラス | H2: Wp_avg (実際配分) | I2: Wb_avg (基準配分) | J2: Rp_avg (実績リターン) | K2: Rb_avg (BMリターン) | L2: R_total (全体BMリターン) | M2: 資産配分効果(AA) | N2: 銘柄選択効果(SS) | O2: トータル効果
A3: 45016 | B3: =IF(A3="","", SUMIFS(計算シート!$V$2:$V$2000, 計算シート!$A$2:$A$2000, A3)) -> 0.012384054 | C3: =IF(A3="","", SUMIFS(計算シート!$W$2:$W$2000, 計算シート!$A$2:$A$2000, A3)) -> 0.0052446002 | D3: =IF(A3="","", B3) -> 0.012384054 | E3: =IF(A3="","", C3) -> 0.0052446002 | G3: =IF('基準資産配分（設定）'!A3="","", '基準資産配分（設定）'!A3) -> 国内債券（固定金利・国債中心） | H3: =IF($G3="","", AVERAGEIFS(計算シート!$U$2:$U$2000, 計算シート!$B$2:$B$2000, $G3)) -> 0.308253 | I3: =IF($G3="","", AVERAGEIFS(計算シート!$R$2:$R$2000, 計算シート!$B$2:$B$2000, $G3)) -> 0.3906 | J3: =IF($G3="","", AVERAGEIFS(計算シート!$P$2:$P$2000, 計算シート!$B$2:$B$2000, $G3)) -> 0.002924892 | K3: =IF($G3="","", AVERAGEIFS(計算シート!$S$2:$S$2000, 計算シート!$B$2:$B$2000, $G3)) -> -0.00032394595 | L3: =IF($G3="","", AVERAGE($C$3:$C$62)) -> 0.0017302555 | M3: =IF($G3="","", (H3-I3)*(K3-L3)) -> 0.00016915732 | N3: =IF($G3="","", H3*(J3-K3)) -> 0.0010014641 | O3: =IF($G3="","", M3+N3) -> 0.0011706214
A4: =IF(A3="","", EOMONTH(A3, 1)) -> 45046 | B4: =IF(A4="","", SUMIFS(計算シート!$V$2:$V$2000, 計算シート!$A$2:$A$2000, A4)) -> 0.0060533581 | C4: =IF(A4="","", SUMIFS(計算シート!$W$2:$W$2000, 計算シート!$A$2:$A$2000, A4)) -> 0.0061774234 | D4: =IF(A4="","", (1+D3)*(1+B4)-1) -> 0.018512377 | E4: =IF(A4="","", (1+E3)*(1+C4)-1) -> 0.011454422 | G4: =IF('基準資産配分（設定）'!A4="","", '基準資産配分（設定）'!A4) -> 国内債券（変動/ASW） | H4: =IF($G4="","", AVERAGEIFS(計算シート!$U$2:$U$2000, 計算シート!$B$2:$B$2000, $G4)) -> 0.13737746 | I4: =IF($G4="","", AVERAGEIFS(計算シート!$R$2:$R$2000, 計算シート!$B$2:$B$2000, $G4)) -> 0.1562 | J4: =IF($G4="","", AVERAGEIFS(計算シート!$P$2:$P$2000, 計算シート!$B$2:$B$2000, $G4)) -> 0.002201411 | K4: =IF($G4="","", AVERAGEIFS(計算シート!$S$2:$S$2000, 計算シート!$B$2:$B$2000, $G4)) -> 0.00078018919 | L4: =IF($G4="","", AVERAGE($C$3:$C$62)) -> 0.0017302555 | M4: =IF($G4="","", (H4-I4)*(K4-L4)) -> 1.788266e-05 | N4: =IF($G4="","", H4*(J4-K4)) -> 0.00019524384 | O4: =IF($G4="","", M4+N4) -> 0.0002131265
A5: =IF(A4="","", EOMONTH(A4, 1)) -> 45077 | B5: =IF(A5="","", SUMIFS(計算シート!$V$2:$V$2000, 計算シート!$A$2:$A$2000, A5)) -> -0.013840504 | C5: =IF(A5="","", SUMIFS(計算シート!$W$2:$W$2000, 計算シート!$A$2:$A$2000, A5)) -> 0.0052232853 | D5: =IF(A5="","", (1+D4)*(1+B5)-1) -> 0.0044156521 | E5: =IF(A5="","", (1+E4)*(1+C5)-1) -> 0.016737537 | G5: =IF('基準資産配分（設定）'!A5="","", '基準資産配分（設定）'!A5) -> 外国債券（為替ヘッジ有・固定） | H5: =IF($G5="","", AVERAGEIFS(計算シート!$U$2:$U$2000, 計算シート!$B$2:$B$2000, $G5)) -> 0.21746353 | I5: =IF($G5="","", AVERAGEIFS(計算シート!$R$2:$R$2000, 計算シート!$B$2:$B$2000, $G5)) -> 0.2344 | J5: =IF($G5="","", AVERAGEIFS(計算シート!$P$2:$P$2000, 計算シート!$B$2:$B$2000, $G5)) -> 0.0087404794 | K5: =IF($G5="","", AVERAGEIFS(計算シート!$S$2:$S$2000, 計算シート!$B$2:$B$2000, $G5)) -> 0.0035467838 | L5: =IF($G5="","", AVERAGE($C$3:$C$62)) -> 0.0017302555 | M5: =IF($G5="","", (H5-I5)*(K5-L5)) -> -3.0765576e-05 | N5: =IF($G5="","", H5*(J5-K5)) -> 0.0011294394 | O5: =IF($G5="","", M5+N5) -> 0.0010986738
A6: =IF(A5="","", EOMONTH(A5, 1)) -> 45107 | B6: =IF(A6="","", SUMIFS(計算シート!$V$2:$V$2000, 計算シート!$A$2:$A$2000, A6)) -> -0.011403603 | C6: =IF(A6="","", SUMIFS(計算シート!$W$2:$W$2000, 計算シート!$A$2:$A$2000, A6)) -> -0.0028445776 | D6: =IF(A6="","", (1+D5)*(1+B6)-1) -> -0.0070383057 | E6: =IF(A6="","", (1+E5)*(1+C6)-1) -> 0.013845348 | G6: =IF('基準資産配分（設定）'!A6="","", '基準資産配分（設定）'!A6) -> 国内株式（純投資） | H6: =IF($G6="","", AVERAGEIFS(計算シート!$U$2:$U$2000, 計算シート!$B$2:$B$2000, $G6)) -> 0.13519521 | I6: =IF($G6="","", AVERAGEIFS(計算シート!$R$2:$R$2000, 計算シート!$B$2:$B$2000, $G6)) -> 0.1172 | J6: =IF($G6="","", AVERAGEIFS(計算シート!$P$2:$P$2000, 計算シート!$B$2:$B$2000, $G6)) -> 0.016811288 | K6: =IF($G6="","", AVERAGEIFS(計算シート!$S$2:$S$2000, 計算シート!$B$2:$B$2000, $G6)) -> 0.011053676 | L6: =IF($G6="","", AVERAGE($C$3:$C$62)) -> 0.0017302555 | M6: =IF($G6="","", (H6-I6)*(K6-L6)) -> 0.00016777687 | N6: =IF($G6="","", H6*(J6-K6)) -> 0.0007784016 | O6: =IF($G6="","", M6+N6) -> 0.00094617847
A7: =IF(A6="","", EOMONTH(A6, 1)) -> 45138 | B7: =IF(A7="","", SUMIFS(計算シート!$V$2:$V$2000, 計算シート!$A$2:$A$2000, A7)) -> 0.00072844242 | C7: =IF(A7="","", SUMIFS(計算シート!$W$2:$W$2000, 計算シート!$A$2:$A$2000, A7)) -> -0.0003086318 | D7: =IF(A7="","", (1+D6)*(1+B7)-1) -> -0.0063149903 | E7: =IF(A7="","", (1+E6)*(1+C7)-1) -> 0.013532443 | G7: =IF('基準資産配分（設定）'!A7="","", '基準資産配分（設定）'!A7) -> 不動産（J-REIT含む） | H7: =IF($G7="","", AVERAGEIFS(計算シート!$U$2:$U$2000, 計算シート!$B$2:$B$2000, $G7)) -> 0.033590045 | I7: =IF($G7="","", AVERAGEIFS(計算シート!$R$2:$R$2000, 計算シート!$B$2:$B$2000, $G7)) -> 0.0391 | J7: =IF($G7="","", AVERAGEIFS(計算シート!$P$2:$P$2000, 計算シート!$B$2:$B$2000, $G7)) -> 0.010317632 | K7: =IF($G7="","", AVERAGEIFS(計算シート!$S$2:$S$2000, 計算シート!$B$2:$B$2000, $G7)) -> 0.0076106216 | L7: =IF($G7="","", AVERAGE($C$3:$C$62)) -> 0.0017302555 | M7: =IF($G7="","", (H7-I7)*(K7-L7)) -> -3.2400551e-05 | N7: =IF($G7="","", H7*(J7-K7)) -> 9.0928608e-05 | O7: =IF($G7="","", M7+N7) -> 5.8528057e-05
A8: =IF(A7="","", EOMONTH(A7, 1)) -> 45169 | B8: =IF(A8="","", SUMIFS(計算シート!$V$2:$V$2000, 計算シート!$A$2:$A$2000, A8)) -> 0.0053038765 | C8: =IF(A8="","", SUMIFS(計算シート!$W$2:$W$2000, 計算シート!$A$2:$A$2000, A8)) -> 0.011036222 | D8: =IF(A8="","", (1+D7)*(1+B8)-1) -> -0.0010446077 | E8: =IF(A8="","", (1+E7)*(1+C8)-1) -> 0.024718012 | G8: =IF('基準資産配分（設定）'!A8="","", '基準資産配分（設定）'!A8) -> マルチアセット・その他投信 | H8: =IF($G8="","", AVERAGEIFS(計算シート!$U$2:$U$2000, 計算シート!$B$2:$B$2000, $G8)) -> 0.058623736 | I8: =IF($G8="","", AVERAGEIFS(計算シート!$R$2:$R$2000, 計算シート!$B$2:$B$2000, $G8)) -> 0.0625 | J8: =IF($G8="","", AVERAGEIFS(計算シート!$P$2:$P$2000, 計算シート!$B$2:$B$2000, $G8)) -> 0.0026207088 | K8: =IF($G8="","", AVERAGEIFS(計算シート!$S$2:$S$2000, 計算シート!$B$2:$B$2000, $G8)) -> 0.016465676 | L8: =IF($G8="","", AVERAGE($C$3:$C$62)) -> 0.0017302555 | M8: =IF($G8="","", (H8-I8)*(K8-L8)) -> -5.7118375e-05 | N8: =IF($G8="","", H8*(J8-K8)) -> -0.00081164369 | O8: =IF($G8="","", M8+N8) -> -0.00086876206
A9: =IF(A8="","", EOMONTH(A8, 1)) -> 45199 | B9: =IF(A9="","", SUMIFS(計算シート!$V$2:$V$2000, 計算シート!$A$2:$A$2000, A9)) -> 0.0081319287 | C9: =IF(A9="","", SUMIFS(計算シート!$W$2:$W$2000, 計算シート!$A$2:$A$2000, A9)) -> 0.0074122041 | D9: =IF(A9="","", (1+D8)*(1+B9)-1) -> 0.0070788263 | E9: =IF(A9="","", (1+E8)*(1+C9)-1) -> 0.032313431 | G9: =IF('基準資産配分（設定）'!A9="","", '基準資産配分（設定）'!A9) -> （参考）政策保有株式 | H9: =IF($G9="","", AVERAGEIFS(計算シート!$U$2:$U$2000, 計算シート!$B$2:$B$2000, $G9)) -> 0.082469993 | I9: =IF($G9="","", AVERAGEIFS(計算シート!$R$2:$R$2000, 計算シート!$B$2:$B$2000, $G9)) -> 0 | J9: =IF($G9="","", AVERAGEIFS(計算シート!$P$2:$P$2000, 計算シート!$B$2:$B$2000, $G9)) -> 0.0071788054 | K9: =IF($G9="","", AVERAGEIFS(計算シート!$S$2:$S$2000, 計算シート!$B$2:$B$2000, $G9)) -> 0.011053676 | L9: =IF($G9="","", AVERAGE($C$3:$C$62)) -> 0.0017302555 | M9: =IF($G9="","", (H9-I9)*(K9-L9)) -> 0.0007689024 | N9: =IF($G9="","", H9*(J9-K9)) -> -0.00031956053 | O9: =IF($G9="","", M9+N9) -> 0.00044934187
A10: =IF(A9="","", EOMONTH(A9, 1)) -> 45230 | B10: =IF(A10="","", SUMIFS(計算シート!$V$2:$V$2000, 計算シート!$A$2:$A$2000, A10)) -> -0.008505868 | C10: =IF(A10="","", SUMIFS(計算シート!$W$2:$W$2000, 計算シート!$A$2:$A$2000, A10)) -> 0.0098549037 | D10: =IF(A10="","", (1+D9)*(1+B10)-1) -> -0.0014872532 | E10: =IF(A10="","", (1+E9)*(1+C10)-1) -> 0.04248678 | G10: 合計 | H10: =SUM(H3:H9) -> 0.97297297 | I10: =SUM(I3:I9) -> 1 | M10: =SUM(M3:M9) -> 0.0010034348 | N10: =SUM(N3:N9) -> 0.0020642733 | O10: =SUM(O3:O9) -> 0.003067708
A11: =IF(A10="","", EOMONTH(A10, 1)) -> 45260 | B11: =IF(A11="","", SUMIFS(計算シート!$V$2:$V$2000, 計算シート!$A$2:$A$2000, A11)) -> 0.0061631345 | C11: =IF(A11="","", SUMIFS(計算シート!$W$2:$W$2000, 計算シート!$A$2:$A$2000, A11)) -> -0.0002446355 | D11: =IF(A11="","", (1+D10)*(1+B11)-1) -> 0.0046667152 | E11: =IF(A11="","", (1+E10)*(1+C11)-1) -> 0.042231751
A12: =IF(A11="","", EOMONTH(A11, 1)) -> 45291 | B12: =IF(A12="","", SUMIFS(計算シート!$V$2:$V$2000, 計算シート!$A$2:$A$2000, A12)) -> 0.010974188 | C12: =IF(A12="","", SUMIFS(計算シート!$W$2:$W$2000, 計算シート!$A$2:$A$2000, A12)) -> 0.016799076 | D12: =IF(A12="","", (1+D11)*(1+B12)-1) -> 0.015692117 | E12: =IF(A12="","", (1+E11)*(1+C12)-1) -> 0.059740282
A13: =IF(A12="","", EOMONTH(A12, 1)) -> 45322 | B13: =IF(A13="","", SUMIFS(計算シート!$V$2:$V$2000, 計算シート!$A$2:$A$2000, A13)) -> 9.4662151e-05 | C13: =IF(A13="","", SUMIFS(計算シート!$W$2:$W$2000, 計算シート!$A$2:$A$2000, A13)) -> 0.019669703 | D13: =IF(A13="","", (1+D12)*(1+B13)-1) -> 0.015788265 | E13: =IF(A13="","", (1+E12)*(1+C13)-1) -> 0.080585058
A14: =IF(A13="","", EOMONTH(A13, 1)) -> 45351 | B14: =IF(A14="","", SUMIFS(計算シート!$V$2:$V$2000, 計算シート!$A$2:$A$2000, A14)) -> 0.013638826 | C14: =IF(A14="","", SUMIFS(計算シート!$W$2:$W$2000, 計算シート!$A$2:$A$2000, A14)) -> 0.0052041079 | D14: =IF(A14="","", (1+D13)*(1+B14)-1) -> 0.029642424 | E14: =IF(A14="","", (1+E13)*(1+C14)-1) -> 0.08620854
A15: =IF(A14="","", EOMONTH(A14, 1)) -> 45382 | B15: =IF(A15="","", SUMIFS(計算シート!$V$2:$V$2000, 計算シート!$A$2:$A$2000, A15)) -> 0.002808217 | C15: =IF(A15="","", SUMIFS(計算シート!$W$2:$W$2000, 計算シート!$A$2:$A$2000, A15)) -> -0.00093219 | D15: =IF(A15="","", (1+D14)*(1+B15)-1) -> 0.032533884 | E15: =IF(A15="","", (1+E14)*(1+C15)-1) -> 0.085195987
A16: =IF(A15="","", EOMONTH(A15, 1)) -> 45412 | B16: =IF(A16="","", SUMIFS(計算シート!$V$2:$V$2000, 計算シート!$A$2:$A$2000, A16)) -> 0.01586301 | C16: =IF(A16="","", SUMIFS(計算シート!$W$2:$W$2000, 計算シート!$A$2:$A$2000, A16)) -> 0.0051032077 | D16: =IF(A16="","", (1+D15)*(1+B16)-1) -> 0.048912979 | E16: =IF(A16="","", (1+E15)*(1+C16)-1) -> 0.090733967
A17: =IF(A16="","", EOMONTH(A16, 1)) -> 45443 | B17: =IF(A17="","", SUMIFS(計算シート!$V$2:$V$2000, 計算シート!$A$2:$A$2000, A17)) -> -0.0018677501 | C17: =IF(A17="","", SUMIFS(計算シート!$W$2:$W$2000, 計算シート!$A$2:$A$2000, A17)) -> 0.015980802 | D17: =IF(A17="","", (1+D16)*(1+B17)-1) -> 0.046953872 | E17: =IF(A17="","", (1+E16)*(1+C17)-1) -> 0.10816477
A18: =IF(A17="","", EOMONTH(A17, 1)) -> 45473 | B18: =IF(A18="","", SUMIFS(計算シート!$V$2:$V$2000, 計算シート!$A$2:$A$2000, A18)) -> -0.012744098 | C18: =IF(A18="","", SUMIFS(計算シート!$W$2:$W$2000, 計算シート!$A$2:$A$2000, A18)) -> 0.0007616111 | D18: =IF(A18="","", (1+D17)*(1+B18)-1) -> 0.033611389 | E18: =IF(A18="","", (1+E17)*(1+C18)-1) -> 0.10900876
A19: =IF(A18="","", EOMONTH(A18, 1)) -> 45504 | B19: =IF(A19="","", SUMIFS(計算シート!$V$2:$V$2000, 計算シート!$A$2:$A$2000, A19)) -> 0.016550544 | C19: =IF(A19="","", SUMIFS(計算シート!$W$2:$W$2000, 計算シート!$A$2:$A$2000, A19)) -> 0.000776544 | D19: =IF(A19="","", (1+D18)*(1+B19)-1) -> 0.05071822 | E19: =IF(A19="","", (1+E18)*(1+C19)-1) -> 0.10986996
A20: =IF(A19="","", EOMONTH(A19, 1)) -> 45535 | B20: =IF(A20="","", SUMIFS(計算シート!$V$2:$V$2000, 計算シート!$A$2:$A$2000, A20)) -> 0.032060909 | C20: =IF(A20="","", SUMIFS(計算シート!$W$2:$W$2000, 計算シート!$A$2:$A$2000, A20)) -> -0.0082615587 | D20: =IF(A20="","", (1+D19)*(1+B20)-1) -> 0.084405201 | E20: =IF(A20="","", (1+E19)*(1+C20)-1) -> 0.1007007
A21: =IF(A20="","", EOMONTH(A20, 1)) -> 45565 | B21: =IF(A21="","", SUMIFS(計算シート!$V$2:$V$2000, 計算シート!$A$2:$A$2000, A21)) -> 0.0014124399 | C21: =IF(A21="","", SUMIFS(計算シート!$W$2:$W$2000, 計算シート!$A$2:$A$2000, A21)) -> -0.011948599 | D21: =IF(A21="","", (1+D20)*(1+B21)-1) -> 0.085936858 | E21: =IF(A21="","", (1+E20)*(1+C21)-1) -> 0.087548869
A22: =IF(A21="","", EOMONTH(A21, 1)) -> 45596 | B22: =IF(A22="","", SUMIFS(計算シート!$V$2:$V$2000, 計算シート!$A$2:$A$2000, A22)) -> -0.007420841 | C22: =IF(A22="","", SUMIFS(計算シート!$W$2:$W$2000, 計算シート!$A$2:$A$2000, A22)) -> 0.0038095439 | D22: =IF(A22="","", (1+D21)*(1+B22)-1) -> 0.077878294 | E22: =IF(A22="","", (1+E21)*(1+C22)-1) -> 0.091691934
... A62: =IF(A61="","", EOMONTH(A61, 1)) -> 46812 | B62: =IF(A62="","", SUMIFS(計算シート!$V$2:$V$2000, 計算シート!$A$2:$A$2000, A62)) -> 0 | C62: =IF(A62="","", SUMIFS(計算シート!$W$2:$W$2000, 計算シート!$A$2:$A$2000, A62)) -> 0 | D62: =IF(A62="","", (1+D61)*(1+B62)-1) -> 0.12630547 | E62: =IF(A62="","", (1+E61)*(1+C62)-1) -> 0.1084261
B63: =SUM(B3:B62) -> 0.12077395 | C63: =SUM(C3:C62) -> 0.10381533
