Workbook

Sheet インプット
A1: ■ 基礎データ
A2: 資産区分 | B2: 時価(億円) | C2: 簿価(億円)
A3: 債券 | B3: 575 | C3: 516
A4: 株式 | B4: 125 | C4: 119
A5: プライベート | B5: 70 | C5: 70
A7: ■ 目標構成比
A8: 資産区分 | B8: 下限 | C8: 中央 | D8: 上限
A9: 伝統資産うち債券 | B9: 0.4 | C9: 0.45 | D9: 0.5
A10: 伝統資産うち株式 | B10: 0.2 | C10: 0.25 | D10: 0.3
A11: プライベート資産 | B11: 0.2 | C11: 0.25 | D11: 0.3
A13: ■ 償還スケジュール(億円・簿価ベース)
A14: 資産区分 | B14: 2026 | C14: 2027 | D14: 2028 | E14: 2029 | F14: 2030
A15: 債券 | B15: 33 | C15: 42 | D15: 31 | E15: 64.5 | F15: 59
A16: 株式 | B16: 20 | C16: 0 | D16: 0 | E16: 0 | F16: 0
A18: ■ 投資額(億円)
A19: 項目 | B19: 2026 | C19: 2027 | D19: 2028 | E19: 2029 | F19: 2030
A20: 伝統資産 | B20: 30 | C20: 15 | D20: 10 | E20: 34 | F20: 15
A21: プライベート | B21: 11.6 | C21: 9.2 | D21: 5.2 | E21: 3 | F21: 1.6
A23: ■ パラメータ（数式で使用・変更可能）
A24: ← オレンジ枠の値を変更するとリターン計算に反映
A26: 項目 | B26: 値 | C26: 説明
A27: 内債デュレーション | B27: 7 | C27: 金利変動に対する価格感応度
A28: ユーロ円債デュレーション | B28: 5
A29: 外債米ドルデュレーション | B29: 6
A30: 外債豪ドルデュレーション | B30: 5.5
A31: ユーロ円債スプレッド(対JGB) | B31: 0.003 | C31: JGB利回りに加算
A32: 外債豪ドルスプレッド(対UST) | B32: 0.005
A33: 豪ドル債 金利感応度係数 | B33: 0.7 | C33: UST変動に対する豪ドル債の感応度
A35: ■ 債券ウェイト（加重平均計算用）
A36: 資産 | B36: 初期時価(億円) | C36: ウェイト
A37: 内債 | B37: 124 | C37: =B37/SUM(B37:B40) -> 0
A38: ユーロ円債 | B38: 187 | C38: =B38/SUM(B37:B40) -> 0
A39: 外債米ドル建て | B39: 158 | C39: =B39/SUM(B37:B40) -> 0
A40: 外債豪ドル建て | B40: 106 | C40: =B40/SUM(B37:B40) -> 0
A43: ■ ハウスビュー（年度末水準） — Bull(楽観)
A44: ← オレンジ枠に日興証券等のデータを入力
A46: 指標 | B46: 現在値 | C46: 2026 | D46: 2027 | E46: 2028 | F46: 2029 | G46: 2030
A47: 日本国債10年利回り(%) | B47: 1.47 | C47: 1.68 | D47: 1.5 | E47: 1.17 | F47: 1.295 | G47: 1.12
A48: 米国債10年利回り(%) | B48: 4.39 | C48: 4.7 | D48: 4.02 | E48: 2.21 | F48: 3.84 | G48: 3.29
A49: ドル/円 | B49: 118.07 | C49: 119.11 | D49: 111.71 | E49: 90.64 | F49: 93.02 | G49: 81.49
A50: 豪ドル/円 | B50: 86.4 | C50: 93.9 | D50: 97.9 | E50: 62.7 | F50: 83.2 | G50: 82.8
A51: TOPIX | B51: 1649.76 | C51: 1681.07 | D51: 1475.68 | E51: 859.24 | F51: 907.59 | G51: 898.8
A54: ■ ハウスビュー（年度末水準） — Base(中央)
A55: ← オレンジ枠に日興証券等のデータを入力
A57: 指標 | B57: 現在値 | C57: 2026 | D57: 2027 | E57: 2028 | F57: 2029 | G57: 2030
A58: 日本国債10年利回り(%) | B58: 2.25 | C58: 2.5 | D58: 2.8 | E58: 2.85 | F58: 2.9 | G58: 2.95
A59: 米国債10年利回り(%) | B59: 4.1 | C59: 3.8 | D59: 4.1 | E59: 4.1 | F59: 4.1 | G59: 4.1
A60: ドル/円 | B60: 153 | C60: 157.10738 | D60: 152.00649 | E60: 152.00649 | F60: 152.00649 | G60: 152.00649
A61: 豪ドル/円 | B61: 109 | C61: 112.08491 | D61: 113.15238 | E61: 111.03738 | F61: 108.96192 | G61: 106.92525
A62: TOPIX | B62: 3930 | C62: 3600.2098 | D62: 3486.4334 | E62: 3328.6422 | F62: 3177.9925 | G62: 3034.1609
A65: ■ ハウスビュー（年度末水準） — Bear(悲観)
A66: ← オレンジ枠に日興証券等のデータを入力
A68: 指標 | B68: 現在値 | C68: 2026 | D68: 2027 | E68: 2028 | F68: 2029 | G68: 2030
A69: 日本国債10年利回り(%) | B69: -0.01 | C69: 0.02 | D69: 0.07 | E69: 0.42 | F69: 0.61 | G69: 1.05
A70: 米国債10年利回り(%) | B70: 1.92 | C70: 0.91 | D70: 1.51 | E70: 3.87 | F70: 3.88 | G70: 4.2
A71: ドル/円 | B71: 108.61 | C71: 103.19 | D71: 115.08 | E71: 131.11 | F71: 141.83 | G71: 158
A72: 豪ドル/円 | B72: 76.1 | C72: 79.4 | D72: 83.4 | E72: 88.9 | F72: 96.6 | G72: 107.4
A73: TOPIX | B73: 1721.36 | C73: 1804.68 | D73: 1992.33 | E73: 1891.71 | F73: 2366.39 | G73: 2784.92
A76: ■ 算出リターン（自動計算） — Bull(楽観)
A77: ※ ハウスビュー＋パラメータから自動算出
A79: 資産 | B79: 2026 | C79: 2027 | D79: 2028 | E79: 2029 | F79: 2030
A80: 内債ﾘﾀｰﾝ | B80: =B47/100-$B$27*(C47-B47)/100 -> 0 | C80: =C47/100-$B$27*(D47-C47)/100 -> 0 | D80: =D47/100-$B$27*(E47-D47)/100 -> 0 | E80: =E47/100-$B$27*(F47-E47)/100 -> 0 | F80: =F47/100-$B$27*(G47-F47)/100 -> 0
A81: ユーロ円債ﾘﾀｰﾝ | B81: =B47/100+$B$31-$B$28*(C47-B47)/100 -> 0 | C81: =C47/100+$B$31-$B$28*(D47-C47)/100 -> 0 | D81: =D47/100+$B$31-$B$28*(E47-D47)/100 -> 0 | E81: =E47/100+$B$31-$B$28*(F47-E47)/100 -> 0 | F81: =F47/100+$B$31-$B$28*(G47-F47)/100 -> 0
A82: 外債米ドルﾘﾀｰﾝ | B82: =B48/100-$B$29*(C48-B48)/100+(C49-B49)/B49 -> 0 | C82: =C48/100-$B$29*(D48-C48)/100+(D49-C49)/C49 -> 0 | D82: =D48/100-$B$29*(E48-D48)/100+(E49-D49)/D49 -> 0 | E82: =E48/100-$B$29*(F48-E48)/100+(F49-E49)/E49 -> 0 | F82: =F48/100-$B$29*(G48-F48)/100+(G49-F49)/F49 -> 0
A83: 外債豪ドルﾘﾀｰﾝ | B83: =B48/100+$B$32-$B$30*(C48-B48)*$B$33/100+(C50-B50)/B50 -> 0 | C83: =C48/100+$B$32-$B$30*(D48-C48)*$B$33/100+(D50-C50)/C50 -> 0 | D83: =D48/100+$B$32-$B$30*(E48-D48)*$B$33/100+(E50-D50)/D50 -> 0 | E83: =E48/100+$B$32-$B$30*(F48-E48)*$B$33/100+(F50-E50)/E50 -> 0 | F83: =F48/100+$B$32-$B$30*(G48-F48)*$B$33/100+(G50-F50)/F50 -> 0
A84: 国内株式ﾘﾀｰﾝ | B84: =(C51-B51)/B51 -> 0 | C84: =(D51-C51)/C51 -> 0 | D84: =(E51-D51)/D51 -> 0 | E84: =(F51-E51)/E51 -> 0 | F84: =(G51-F51)/F51 -> 0
A85: 債券加重平均ﾘﾀｰﾝ | B85: =$C$37*B80+$C$38*B81+$C$39*B82+$C$40*B83 -> 0 | C85: =$C$37*C80+$C$38*C81+$C$39*C82+$C$40*C83 -> 0 | D85: =$C$37*D80+$C$38*D81+$C$39*D82+$C$40*D83 -> 0 | E85: =$C$37*E80+$C$38*E81+$C$39*E82+$C$40*E83 -> 0 | F85: =$C$37*F80+$C$38*F81+$C$39*F82+$C$40*F83 -> 0
A86: 株式ﾘﾀｰﾝ | B86: =B84 -> 0 | C86: =C84 -> 0 | D86: =D84 -> 0 | E86: =E84 -> 0 | F86: =F84 -> 0
A89: ■ 算出リターン（自動計算） — Base(中央)
A90: ※ ハウスビュー＋パラメータから自動算出
A92: 資産 | B92: 2026 | C92: 2027 | D92: 2028 | E92: 2029 | F92: 2030
A93: 内債ﾘﾀｰﾝ | B93: =B58/100-$B$27*(C58-B58)/100 -> 0 | C93: =C58/100-$B$27*(D58-C58)/100 -> 0 | D93: =D58/100-$B$27*(E58-D58)/100 -> 0 | E93: =E58/100-$B$27*(F58-E58)/100 -> 0 | F93: =F58/100-$B$27*(G58-F58)/100 -> 0
A94: ユーロ円債ﾘﾀｰﾝ | B94: =B58/100+$B$31-$B$28*(C58-B58)/100 -> 0 | C94: =C58/100+$B$31-$B$28*(D58-C58)/100 -> 0 | D94: =D58/100+$B$31-$B$28*(E58-D58)/100 -> 0 | E94: =E58/100+$B$31-$B$28*(F58-E58)/100 -> 0 | F94: =F58/100+$B$31-$B$28*(G58-F58)/100 -> 0
A95: 外債米ドルﾘﾀｰﾝ | B95: =B59/100-$B$29*(C59-B59)/100+(C60-B60)/B60 -> 0 | C95: =C59/100-$B$29*(D59-C59)/100+(D60-C60)/C60 -> 0 | D95: =D59/100-$B$29*(E59-D59)/100+(E60-D60)/D60 -> 0 | E95: =E59/100-$B$29*(F59-E59)/100+(F60-E60)/E60 -> 0 | F95: =F59/100-$B$29*(G59-F59)/100+(G60-F60)/F60 -> 0
A96: 外債豪ドルﾘﾀｰﾝ | B96: =B59/100+$B$32-$B$30*(C59-B59)*$B$33/100+(C61-B61)/B61 -> 0 | C96: =C59/100+$B$32-$B$30*(D59-C59)*$B$33/100+(D61-C61)/C61 -> 0 | D96: =D59/100+$B$32-$B$30*(E59-D59)*$B$33/100+(E61-D61)/D61 -> 0 | E96: =E59/100+$B$32-$B$30*(F59-E59)*$B$33/100+(F61-E61)/E61 -> 0 | F96: =F59/100+$B$32-$B$30*(G59-F59)*$B$33/100+(G61-F61)/F61 -> 0
A97: 国内株式ﾘﾀｰﾝ | B97: =(C62-B62)/B62 -> 0 | C97: =(D62-C62)/C62 -> 0 | D97: =(E62-D62)/D62 -> 0 | E97: =(F62-E62)/E62 -> 0 | F97: =(G62-F62)/F62 -> 0
A98: 債券加重平均ﾘﾀｰﾝ | B98: =$C$37*B93+$C$38*B94+$C$39*B95+$C$40*B96 -> 0 | C98: =$C$37*C93+$C$38*C94+$C$39*C95+$C$40*C96 -> 0 | D98: =$C$37*D93+$C$38*D94+$C$39*D95+$C$40*D96 -> 0 | E98: =$C$37*E93+$C$38*E94+$C$39*E95+$C$40*E96 -> 0 | F98: =$C$37*F93+$C$38*F94+$C$39*F95+$C$40*F96 -> 0
A99: 株式ﾘﾀｰﾝ | B99: =B97 -> 0 | C99: =C97 -> 0 | D99: =D97 -> 0 | E99: =E97 -> 0 | F99: =F97 -> 0
A102: ■ 算出リターン（自動計算） — Bear(悲観)
A103: ※ ハウスビュー＋パラメータから自動算出
A105: 資産 | B105: 2026 | C105: 2027 | D105: 2028 | E105: 2029 | F105: 2030
A106: 内債ﾘﾀｰﾝ | B106: =B69/100-$B$27*(C69-B69)/100 -> 0 | C106: =C69/100-$B$27*(D69-C69)/100 -> 0 | D106: =D69/100-$B$27*(E69-D69)/100 -> 0 | E106: =E69/100-$B$27*(F69-E69)/100 -> 0 | F106: =F69/100-$B$27*(G69-F69)/100 -> 0
A107: ユーロ円債ﾘﾀｰﾝ | B107: =B69/100+$B$31-$B$28*(C69-B69)/100 -> 0 | C107: =C69/100+$B$31-$B$28*(D69-C69)/100 -> 0 | D107: =D69/100+$B$31-$B$28*(E69-D69)/100 -> 0 | E107: =E69/100+$B$31-$B$28*(F69-E69)/100 -> 0 | F107: =F69/100+$B$31-$B$28*(G69-F69)/100 -> 0
A108: 外債米ドルﾘﾀｰﾝ | B108: =B70/100-$B$29*(C70-B70)/100+(C71-B71)/B71 -> 0 | C108: =C70/100-$B$29*(D70-C70)/100+(D71-C71)/C71 -> 0 | D108: =D70/100-$B$29*(E70-D70)/100+(E71-D71)/D71 -> 0 | E108: =E70/100-$B$29*(F70-E70)/100+(F71-E71)/E71 -> 0 | F108: =F70/100-$B$29*(G70-F70)/100+(G71-F71)/F71 -> 0
A109: 外債豪ドルﾘﾀｰﾝ | B109: =B70/100+$B$32-$B$30*(C70-B70)*$B$33/100+(C72-B72)/B72 -> 0 | C109: =C70/100+$B$32-$B$30*(D70-C70)*$B$33/100+(D72-C72)/C72 -> 0 | D109: =D70/100+$B$32-$B$30*(E70-D70)*$B$33/100+(E72-D72)/D72 -> 0 | E109: =E70/100+$B$32-$B$30*(F70-E70)*$B$33/100+(F72-E72)/E72 -> 0 | F109: =F70/100+$B$32-$B$30*(G70-F70)*$B$33/100+(G72-F72)/F72 -> 0
A110: 国内株式ﾘﾀｰﾝ | B110: =(C73-B73)/B73 -> 0 | C110: =(D73-C73)/C73 -> 0 | D110: =(E73-D73)/D73 -> 0 | E110: =(F73-E73)/E73 -> 0 | F110: =(G73-F73)/F73 -> 0
A111: 債券加重平均ﾘﾀｰﾝ | B111: =$C$37*B106+$C$38*B107+$C$39*B108+$C$40*B109 -> 0 | C111: =$C$37*C106+$C$38*C107+$C$39*C108+$C$40*C109 -> 0 | D111: =$C$37*D106+$C$38*D107+$C$39*D108+$C$40*D109 -> 0 | E111: =$C$37*E106+$C$38*E107+$C$39*E108+$C$40*E109 -> 0 | F111: =$C$37*F106+$C$38*F107+$C$39*F108+$C$40*F109 -> 0
A112: 株式ﾘﾀｰﾝ | B112: =B110 -> 0 | C112: =C110 -> 0 | D112: =D110 -> 0 | E112: =E110 -> 0 | F112: =F110 -> 0
A115: ■ 最適配分（逆算結果・参考）
A116: シナリオ | B116: 2026 | C116: 2027 | D116: 2028 | E116: 2029 | F116: 2030
A117: Bull(楽観) | B117: 1 | C117: 1 | D117: 1 | E117: 1 | F117: 1
A118: Base(中央) | B118: 1 | C118: 1 | D118: 1 | E118: 1 | F118: 1
A119: Bear(悲観) | B119: 0.31 | C119: 1 | D119: 1 | E119: 1 | F119: 1

Sheet Bull
A1: ■ Bull(楽観) シミュレーション
A2: 配分比率(オレンジ枠)を変更可。リターンはインプットシートから自動計算。
A3: 株式配分比率 ← 変更可 | C3: 1 | D3: 1 | E3: 1 | F3: 1 | G3: 1
A4: 債券配分比率 | C4: =1-C3 -> 0 | D4: =1-D3 -> 0 | E4: =1-E3 -> 0 | F4: =1-F3 -> 0 | G4: =1-G3 -> 0
A6: 債券期待ﾘﾀｰﾝ(自動) | C6: ='インプット'!B85 -> 0 | D6: ='インプット'!C85 -> 0 | E6: ='インプット'!D85 -> 0 | F6: ='インプット'!E85 -> 0 | G6: ='インプット'!F85 -> 0
A7: 株式期待ﾘﾀｰﾝ(自動) | C7: ='インプット'!B86 -> 0 | D7: ='インプット'!C86 -> 0 | E7: ='インプット'!D86 -> 0 | F7: ='インプット'!E86 -> 0 | G7: ='インプット'!F86 -> 0
B9: 現状 | C9: 2026 | D9: 2027 | E9: 2028 | F9: 2029 | G9: 2030 | H9: 目標
A10: 債券償還(簿価) | B10: 0 | C10: ='インプット'!B15 -> 0 | D10: ='インプット'!C15 -> 0 | E10: ='インプット'!D15 -> 0 | F10: ='インプット'!E15 -> 0 | G10: ='インプット'!F15 -> 0
A11: 株式償還 | B11: 0 | C11: ='インプット'!B16 -> 0 | D11: ='インプット'!C16 -> 0 | E11: ='インプット'!D16 -> 0 | F11: ='インプット'!E16 -> 0 | G11: ='インプット'!F16 -> 0
A12: 伝統資産投資 | B12: 0 | C12: ='インプット'!B20 -> 0 | D12: ='インプット'!C20 -> 0 | E12: ='インプット'!D20 -> 0 | F12: ='インプット'!E20 -> 0 | G12: ='インプット'!F20 -> 0
A13: ﾌﾟﾗｲﾍﾞｰﾄ投資 | B13: 0 | C13: ='インプット'!B21 -> 0 | D13: ='インプット'!C21 -> 0 | E13: ='インプット'!D21 -> 0 | F13: ='インプット'!E21 -> 0 | G13: ='インプット'!F21 -> 0
A14: → 債券投資 | B14: 0 | C14: =C12*(1-C3) -> 0 | D14: =D12*(1-D3) -> 0 | E14: =E12*(1-E3) -> 0 | F14: =F12*(1-F3) -> 0 | G14: =G12*(1-G3) -> 0
A15: → 株式投資 | B15: 0 | C15: =C12*C3 -> 0 | D15: =D12*D3 -> 0 | E15: =E12*E3 -> 0 | F15: =F12*F3 -> 0 | G15: =G12*G3 -> 0
A17: 債券残高(時価) | B17: ='インプット'!B3 -> 0 | C17: =(B17-C10)*(1+C6)+C14 -> 0 | D17: =(C17-D10)*(1+D6)+D14 -> 0 | E17: =(D17-E10)*(1+E6)+E14 -> 0 | F17: =(E17-F10)*(1+F6)+F14 -> 0 | G17: =(F17-G10)*(1+G6)+G14 -> 0
A18: 株式残高(時価) | B18: ='インプット'!B4 -> 0 | C18: =(B18-C11)*(1+C7)+C15 -> 0 | D18: =(C18-D11)*(1+D7)+D15 -> 0 | E18: =(D18-E11)*(1+E7)+E15 -> 0 | F18: =(E18-F11)*(1+F7)+F15 -> 0 | G18: =(F18-G11)*(1+G7)+G15 -> 0
A19: ﾌﾟﾗｲﾍﾞｰﾄ残高 | B19: ='インプット'!B5 -> 0 | C19: =B19+C13 -> 0 | D19: =C19+D13 -> 0 | E19: =D19+E13 -> 0 | F19: =E19+F13 -> 0 | G19: =F19+G13 -> 0
A20: 合計(時価) | B20: =B17+B18+B19 -> 0 | C20: =C17+C18+C19 -> 0 | D20: =D17+D18+D19 -> 0 | E20: =E17+E18+E19 -> 0 | F20: =F17+F18+F19 -> 0 | G20: =G17+G18+G19 -> 0
A22: 債券構成比 | B22: =B17/B20 -> 0 | C22: =C17/C20 -> 0 | D22: =D17/D20 -> 0 | E22: =E17/E20 -> 0 | F22: =F17/F20 -> 0 | G22: =G17/G20 -> 0 | H22: 0.45
A23: 株式構成比 | B23: =B18/B20 -> 0 | C23: =C18/C20 -> 0 | D23: =D18/D20 -> 0 | E23: =E18/E20 -> 0 | F23: =F18/F20 -> 0 | G23: =G18/G20 -> 0 | H23: 0.25
A24: ﾌﾟﾗｲﾍﾞｰﾄ構成比 | B24: =B19/B20 -> 0 | C24: =C19/C20 -> 0 | D24: =D19/D20 -> 0 | E24: =E19/E20 -> 0 | F24: =F19/F20 -> 0 | G24: =G19/G20 -> 0 | H24: 0.25
A26: 債券残高(簿価) | B26: ='インプット'!C3 -> 0 | C26: =B26-C10+C14 -> 0 | D26: =C26-D10+D14 -> 0 | E26: =D26-E10+E14 -> 0 | F26: =E26-F10+F14 -> 0 | G26: =F26-G10+G14 -> 0
A27: 株式残高(簿価) | B27: ='インプット'!C4 -> 0 | C27: =B27-C11+C15 -> 0 | D27: =C27-D11+D15 -> 0 | E27: =D27-E11+E15 -> 0 | F27: =E27-F11+F15 -> 0 | G27: =F27-G11+G15 -> 0
A28: ﾌﾟﾗｲﾍﾞｰﾄ(簿価) | B28: ='インプット'!C5 -> 0 | C28: =B28+C13 -> 0 | D28: =C28+D13 -> 0 | E28: =D28+E13 -> 0 | F28: =E28+F13 -> 0 | G28: =F28+G13 -> 0
A29: 合計(簿価) | B29: =B26+B27+B28 -> 0 | C29: =C26+C27+C28 -> 0 | D29: =D26+D27+D28 -> 0 | E29: =E26+E27+E28 -> 0 | F29: =F26+F27+F28 -> 0 | G29: =G26+G27+G28 -> 0
A31: 評価損益(債券) | B31: 0 | C31: =C17-C26 -> 0 | D31: =D17-D26 -> 0 | E31: =E17-E26 -> 0 | F31: =F17-F26 -> 0 | G31: =G17-G26 -> 0
A32: 評価損益(株式) | B32: 0 | C32: =C18-C27 -> 0 | D32: =D18-D27 -> 0 | E32: =E18-E27 -> 0 | F32: =F18-F27 -> 0 | G32: =G18-G27 -> 0

Sheet Base
A1: ■ Base(中央) シミュレーション
A2: 配分比率(オレンジ枠)を変更可。リターンはインプットシートから自動計算。
A3: 株式配分比率 ← 変更可 | C3: 1 | D3: 1 | E3: 1 | F3: 1 | G3: 1
A4: 債券配分比率 | C4: =1-C3 -> 0 | D4: =1-D3 -> 0 | E4: =1-E3 -> 0 | F4: =1-F3 -> 0 | G4: =1-G3 -> 0
A6: 債券期待ﾘﾀｰﾝ(自動) | C6: ='インプット'!B98 -> 0 | D6: ='インプット'!C98 -> 0 | E6: ='インプット'!D98 -> 0 | F6: ='インプット'!E98 -> 0 | G6: ='インプット'!F98 -> 0
A7: 株式期待ﾘﾀｰﾝ(自動) | C7: ='インプット'!B99 -> 0 | D7: ='インプット'!C99 -> 0 | E7: ='インプット'!D99 -> 0 | F7: ='インプット'!E99 -> 0 | G7: ='インプット'!F99 -> 0
B9: 現状 | C9: 2026 | D9: 2027 | E9: 2028 | F9: 2029 | G9: 2030 | H9: 目標
A10: 債券償還(簿価) | B10: 0 | C10: ='インプット'!B15 -> 0 | D10: ='インプット'!C15 -> 0 | E10: ='インプット'!D15 -> 0 | F10: ='インプット'!E15 -> 0 | G10: ='インプット'!F15 -> 0
A11: 株式償還 | B11: 0 | C11: ='インプット'!B16 -> 0 | D11: ='インプット'!C16 -> 0 | E11: ='インプット'!D16 -> 0 | F11: ='インプット'!E16 -> 0 | G11: ='インプット'!F16 -> 0
A12: 伝統資産投資 | B12: 0 | C12: ='インプット'!B20 -> 0 | D12: ='インプット'!C20 -> 0 | E12: ='インプット'!D20 -> 0 | F12: ='インプット'!E20 -> 0 | G12: ='インプット'!F20 -> 0
A13: ﾌﾟﾗｲﾍﾞｰﾄ投資 | B13: 0 | C13: ='インプット'!B21 -> 0 | D13: ='インプット'!C21 -> 0 | E13: ='インプット'!D21 -> 0 | F13: ='インプット'!E21 -> 0 | G13: ='インプット'!F21 -> 0
A14: → 債券投資 | B14: 0 | C14: =C12*(1-C3) -> 0 | D14: =D12*(1-D3) -> 0 | E14: =E12*(1-E3) -> 0 | F14: =F12*(1-F3) -> 0 | G14: =G12*(1-G3) -> 0
A15: → 株式投資 | B15: 0 | C15: =C12*C3 -> 0 | D15: =D12*D3 -> 0 | E15: =E12*E3 -> 0 | F15: =F12*F3 -> 0 | G15: =G12*G3 -> 0
A17: 債券残高(時価) | B17: ='インプット'!B3 -> 0 | C17: =(B17-C10)*(1+C6)+C14 -> 0 | D17: =(C17-D10)*(1+D6)+D14 -> 0 | E17: =(D17-E10)*(1+E6)+E14 -> 0 | F17: =(E17-F10)*(1+F6)+F14 -> 0 | G17: =(F17-G10)*(1+G6)+G14 -> 0
A18: 株式残高(時価) | B18: ='インプット'!B4 -> 0 | C18: =(B18-C11)*(1+C7)+C15 -> 0 | D18: =(C18-D11)*(1+D7)+D15 -> 0 | E18: =(D18-E11)*(1+E7)+E15 -> 0 | F18: =(E18-F11)*(1+F7)+F15 -> 0 | G18: =(F18-G11)*(1+G7)+G15 -> 0
A19: ﾌﾟﾗｲﾍﾞｰﾄ残高 | B19: ='インプット'!B5 -> 0 | C19: =B19+C13 -> 0 | D19: =C19+D13 -> 0 | E19: =D19+E13 -> 0 | F19: =E19+F13 -> 0 | G19: =F19+G13 -> 0
A20: 合計(時価) | B20: =B17+B18+B19 -> 0 | C20: =C17+C18+C19 -> 0 | D20: =D17+D18+D19 -> 0 | E20: =E17+E18+E19 -> 0 | F20: =F17+F18+F19 -> 0 | G20: =G17+G18+G19 -> 0
A22: 債券構成比 | B22: =B17/B20 -> 0 | C22: =C17/C20 -> 0 | D22: =D17/D20 -> 0 | E22: =E17/E20 -> 0 | F22: =F17/F20 -> 0 | G22: =G17/G20 -> 0 | H22: 0.45
A23: 株式構成比 | B23: =B18/B20 -> 0 | C23: =C18/C20 -> 0 | D23: =D18/D20 -> 0 | E23: =E18/E20 -> 0 | F23: =F18/F20 -> 0 | G23: =G18/G20 -> 0 | H23: 0.25
A24: ﾌﾟﾗｲﾍﾞｰﾄ構成比 | B24: =B19/B20 -> 0 | C24: =C19/C20 -> 0 | D24: =D19/D20 -> 0 | E24: =E19/E20 -> 0 | F24: =F19/F20 -> 0 | G24: =G19/G20 -> 0 | H24: 0.25
A26: 債券残高(簿価) | B26: ='インプット'!C3 -> 0 | C26: =B26-C10+C14 -> 0 | D26: =C26-D10+D14 -> 0 | E26: =D26-E10+E14 -> 0 | F26: =E26-F10+F14 -> 0 | G26: =F26-G10+G14 -> 0
A27: 株式残高(簿価) | B27: ='インプット'!C4 -> 0 | C27: =B27-C11+C15 -> 0 | D27: =C27-D11+D15 -> 0 | E27: =D27-E11+E15 -> 0 | F27: =E27-F11+F15 -> 0 | G27: =F27-G11+G15 -> 0
A28: ﾌﾟﾗｲﾍﾞｰﾄ(簿価) | B28: ='インプット'!C5 -> 0 | C28: =B28+C13 -> 0 | D28: =C28+D13 -> 0 | E28: =D28+E13 -> 0 | F28: =E28+F13 -> 0 | G28: =F28+G13 -> 0
A29: 合計(簿価) | B29: =B26+B27+B28 -> 0 | C29: =C26+C27+C28 -> 0 | D29: =D26+D27+D28 -> 0 | E29: =E26+E27+E28 -> 0 | F29: =F26+F27+F28 -> 0 | G29: =G26+G27+G28 -> 0
A31: 評価損益(債券) | B31: 0 | C31: =C17-C26 -> 0 | D31: =D17-D26 -> 0 | E31: =E17-E26 -> 0 | F31: =F17-F26 -> 0 | G31: =G17-G26 -> 0
A32: 評価損益(株式) | B32: 0 | C32: =C18-C27 -> 0 | D32: =D18-D27 -> 0 | E32: =E18-E27 -> 0 | F32: =F18-F27 -> 0 | G32: =G18-G27 -> 0

Sheet Bear
A1: ■ Bear(悲観) シミュレーション
A2: 配分比率(オレンジ枠)を変更可。リターンはインプットシートから自動計算。
A3: 株式配分比率 ← 変更可 | C3: 0.31 | D3: 1 | E3: 1 | F3: 1 | G3: 1
A4: 債券配分比率 | C4: =1-C3 -> 0 | D4: =1-D3 -> 0 | E4: =1-E3 -> 0 | F4: =1-F3 -> 0 | G4: =1-G3 -> 0
A6: 債券期待ﾘﾀｰﾝ(自動) | C6: ='インプット'!B111 -> 0 | D6: ='インプット'!C111 -> 0 | E6: ='インプット'!D111 -> 0 | F6: ='インプット'!E111 -> 0 | G6: ='インプット'!F111 -> 0
A7: 株式期待ﾘﾀｰﾝ(自動) | C7: ='インプット'!B112 -> 0 | D7: ='インプット'!C112 -> 0 | E7: ='インプット'!D112 -> 0 | F7: ='インプット'!E112 -> 0 | G7: ='インプット'!F112 -> 0
B9: 現状 | C9: 2026 | D9: 2027 | E9: 2028 | F9: 2029 | G9: 2030 | H9: 目標
A10: 債券償還(簿価) | B10: 0 | C10: ='インプット'!B15 -> 0 | D10: ='インプット'!C15 -> 0 | E10: ='インプット'!D15 -> 0 | F10: ='インプット'!E15 -> 0 | G10: ='インプット'!F15 -> 0
A11: 株式償還 | B11: 0 | C11: ='インプット'!B16 -> 0 | D11: ='インプット'!C16 -> 0 | E11: ='インプット'!D16 -> 0 | F11: ='インプット'!E16 -> 0 | G11: ='インプット'!F16 -> 0
A12: 伝統資産投資 | B12: 0 | C12: ='インプット'!B20 -> 0 | D12: ='インプット'!C20 -> 0 | E12: ='インプット'!D20 -> 0 | F12: ='インプット'!E20 -> 0 | G12: ='インプット'!F20 -> 0
A13: ﾌﾟﾗｲﾍﾞｰﾄ投資 | B13: 0 | C13: ='インプット'!B21 -> 0 | D13: ='インプット'!C21 -> 0 | E13: ='インプット'!D21 -> 0 | F13: ='インプット'!E21 -> 0 | G13: ='インプット'!F21 -> 0
A14: → 債券投資 | B14: 0 | C14: =C12*(1-C3) -> 0 | D14: =D12*(1-D3) -> 0 | E14: =E12*(1-E3) -> 0 | F14: =F12*(1-F3) -> 0 | G14: =G12*(1-G3) -> 0
A15: → 株式投資 | B15: 0 | C15: =C12*C3 -> 0 | D15: =D12*D3 -> 0 | E15: =E12*E3 -> 0 | F15: =F12*F3 -> 0 | G15: =G12*G3 -> 0
A17: 債券残高(時価) | B17: ='インプット'!B3 -> 0 | C17: =(B17-C10)*(1+C6)+C14 -> 0 | D17: =(C17-D10)*(1+D6)+D14 -> 0 | E17: =(D17-E10)*(1+E6)+E14 -> 0 | F17: =(E17-F10)*(1+F6)+F14 -> 0 | G17: =(F17-G10)*(1+G6)+G14 -> 0
A18: 株式残高(時価) | B18: ='インプット'!B4 -> 0 | C18: =(B18-C11)*(1+C7)+C15 -> 0 | D18: =(C18-D11)*(1+D7)+D15 -> 0 | E18: =(D18-E11)*(1+E7)+E15 -> 0 | F18: =(E18-F11)*(1+F7)+F15 -> 0 | G18: =(F18-G11)*(1+G7)+G15 -> 0
A19: ﾌﾟﾗｲﾍﾞｰﾄ残高 | B19: ='インプット'!B5 -> 0 | C19: =B19+C13 -> 0 | D19: =C19+D13 -> 0 | E19: =D19+E13 -> 0 | F19: =E19+F13 -> 0 | G19: =F19+G13 -> 0
A20: 合計(時価) | B20: =B17+B18+B19 -> 0 | C20: =C17+C18+C19 -> 0 | D20: =D17+D18+D19 -> 0 | E20: =E17+E18+E19 -> 0 | F20: =F17+F18+F19 -> 0 | G20: =G17+G18+G19 -> 0
A22: 債券構成比 | B22: =B17/B20 -> 0 | C22: =C17/C20 -> 0 | D22: =D17/D20 -> 0 | E22: =E17/E20 -> 0 | F22: =F17/F20 -> 0 | G22: =G17/G20 -> 0 | H22: 0.45
A23: 株式構成比 | B23: =B18/B20 -> 0 | C23: =C18/C20 -> 0 | D23: =D18/D20 -> 0 | E23: =E18/E20 -> 0 | F23: =F18/F20 -> 0 | G23: =G18/G20 -> 0 | H23: 0.25
A24: ﾌﾟﾗｲﾍﾞｰﾄ構成比 | B24: =B19/B20 -> 0 | C24: =C19/C20 -> 0 | D24: =D19/D20 -> 0 | E24: =E19/E20 -> 0 | F24: =F19/F20 -> 0 | G24: =G19/G20 -> 0 | H24: 0.25
A26: 債券残高(簿価) | B26: ='インプット'!C3 -> 0 | C26: =B26-C10+C14 -> 0 | D26: =C26-D10+D14 -> 0 | E26: =D26-E10+E14 -> 0 | F26: =E26-F10+F14 -> 0 | G26: =F26-G10+G14 -> 0
A27: 株式残高(簿価) | B27: ='インプット'!C4 -> 0 | C27: =B27-C11+C15 -> 0 | D27: =C27-D11+D15 -> 0 | E27: =D27-E11+E15 -> 0 | F27: =E27-F11+F15 -> 0 | G27: =F27-G11+G15 -> 0
A28: ﾌﾟﾗｲﾍﾞｰﾄ(簿価) | B28: ='インプット'!C5 -> 0 | C28: =B28+C13 -> 0 | D28: =C28+D13 -> 0 | E28: =D28+E13 -> 0 | F28: =E28+F13 -> 0 | G28: =F28+G13 -> 0
A29: 合計(簿価) | B29: =B26+B27+B28 -> 0 | C29: =C26+C27+C28 -> 0 | D29: =D26+D27+D28 -> 0 | E29: =E26+E27+E28 -> 0 | F29: =F26+F27+F28 -> 0 | G29: =G26+G27+G28 -> 0
A31: 評価損益(債券) | B31: 0 | C31: =C17-C26 -> 0 | D31: =D17-D26 -> 0 | E31: =E17-E26 -> 0 | F31: =F17-F26 -> 0 | G31: =G17-G26 -> 0
A32: 評価損益(株式) | B32: 0 | C32: =C18-C27 -> 0 | D32: =D18-D27 -> 0 | E32: =E18-E27 -> 0 | F32: =F18-F27 -> 0 | G32: =G18-G27 -> 0
